codingnow/__init__.py
codingnow/codingTest.py
codingnow/core.py
codingnow/ai/car_driving/car.py
codingnow/ai/car_driving/__pycache__/car.cpython-38.pyc
codingnow/game/platform/block.py
codingnow/game/platform/bullet.py
codingnow/game/platform/bullet_monster.py
codingnow/game/platform/coin.py
codingnow/game/platform/exitdoor.py
codingnow/game/platform/hp.py
codingnow/game/platform/lava.py
codingnow/game/platform/monster.py
codingnow/game/platform/platformGame.py
codingnow/game/platform/player.py
codingnow/game/platform/teleport.py
codingnow/game/platform/weapon.py
codingnow/game/platform/__pycache__/block.cpython-38.pyc
codingnow/game/platform/__pycache__/bullet.cpython-38.pyc
codingnow/game/platform/__pycache__/coin.cpython-38.pyc
codingnow/game/platform/__pycache__/exitdoor.cpython-38.pyc
codingnow/game/platform/__pycache__/hp.cpython-38.pyc
codingnow/game/platform/__pycache__/lava.cpython-38.pyc
codingnow/game/platform/__pycache__/monster.cpython-38.pyc
codingnow/game/platform/__pycache__/platform.cpython-38.pyc
codingnow/game/platform/__pycache__/platformGame.cpython-38.pyc
codingnow/game/platform/__pycache__/player.cpython-38.pyc
codingnow/game/platform/__pycache__/weapon.cpython-38.pyc
codingnow/game/platform/exam/main01.py
codingnow/game/platform/exam/main02.py
codingnow/game/platform/exam/main_0_1_11.py
codingnow/game/platform/exam/__pycache__/main01.cpython-38.pyc
codingnow/game/platform/exam/__pycache__/main02.cpython-38.pyc
codingnow/game/platform/exam/__pycache__/main_0_1_11.cpython-38.pyc
codingnow/game/spacewar/drawBg.py
codingnow/game/spacewar/drawMsg.py
codingnow/game/spacewar/enemy.py
codingnow/game/spacewar/items.py
codingnow/game/spacewar/player.py
codingnow/game/spacewar/spacewarGame.py
codingnow/game/spacewar/weapon.py
codingnow/game/spacewar/__pycache__/drawBg.cpython-38.pyc
codingnow/game/spacewar/__pycache__/drawMsg.cpython-38.pyc
codingnow/game/spacewar/__pycache__/enemy.cpython-38.pyc
codingnow/game/spacewar/__pycache__/items.cpython-38.pyc
codingnow-0.1.52.dist-info/LICENSE
codingnow-0.1.52.dist-info/METADATA
codingnow-0.1.52.dist-info/WHEEL
codingnow-0.1.52.dist-info/top_level.txt
codingnow-0.1.52.dist-info/RECORD
