Metadata-Version: 2.1
Name: codingnow
Version: 0.1.52
Summary: A simple example Python package
Home-page: https://github.com/cflab2017/codingnow_py
Author: codingnow
Author-email: codingnow@naver.com
License: UNKNOWN
Platform: UNKNOWN
Classifier: Programming Language :: Python :: 3
Classifier: License :: OSI Approved :: MIT License
Classifier: Operating System :: OS Independent
Requires-Python: >=3.6
License-File: LICENSE
